LICENSE.txt
MANIFEST.in
README
setup.py
Cluster_Ensembles.egg-info/PKG-INFO
Cluster_Ensembles.egg-info/SOURCES.txt
Cluster_Ensembles.egg-info/dependency_links.txt
Cluster_Ensembles.egg-info/requires.txt
Cluster_Ensembles.egg-info/top_level.txt
src/Cluster_Ensembles/Cluster_Ensembles.py
src/Cluster_Ensembles/__init__.py
src/Cluster_Ensembles/Hypergraph_Partitioning/hmetis-1.5-linux/hmetis
src/Cluster_Ensembles/Hypergraph_Partitioning/hmetis-1.5-linux/khmetis
src/Cluster_Ensembles/Hypergraph_Partitioning/hmetis-1.5-linux/shmetis
src/Cluster_Ensembles/Hypergraph_Partitioning/hmetis-1.5-osx-i686/hmetis
src/Cluster_Ensembles/Hypergraph_Partitioning/hmetis-1.5-osx-i686/khmetis
src/Cluster_Ensembles/Hypergraph_Partitioning/hmetis-1.5-osx-i686/shmetis
src/Cluster_Ensembles/Hypergraph_Partitioning/metis-5.1.0/BUILD-Windows.txt
src/Cluster_Ensembles/Hypergraph_Partitioning/metis-5.1.0/BUILD.txt
src/Cluster_Ensembles/Hypergraph_Partitioning/metis-5.1.0/CMakeLists.txt
src/Cluster_Ensembles/Hypergraph_Partitioning/metis-5.1.0/Changelog
src/Cluster_Ensembles/Hypergraph_Partitioning/metis-5.1.0/Install.txt
src/Cluster_Ensembles/Hypergraph_Partitioning/metis-5.1.0/LICENSE.txt
src/Cluster_Ensembles/Hypergraph_Partitioning/metis-5.1.0/Makefile
src/Cluster_Ensembles/Hypergraph_Partitioning/metis-5.1.0/vsgen.bat
src/Cluster_Ensembles/Hypergraph_Partitioning/metis-5.1.0/GKlib/BUILD.txt
src/Cluster_Ensembles/Hypergraph_Partitioning/metis-5.1.0/GKlib/CMakeLists.txt
src/Cluster_Ensembles/Hypergraph_Partitioning/metis-5.1.0/GKlib/GKlib.h
src/Cluster_Ensembles/Hypergraph_Partitioning/metis-5.1.0/GKlib/GKlibSystem.cmake
src/Cluster_Ensembles/Hypergraph_Partitioning/metis-5.1.0/GKlib/Makefile
src/Cluster_Ensembles/Hypergraph_Partitioning/metis-5.1.0/GKlib/b64.c
src/Cluster_Ensembles/Hypergraph_Partitioning/metis-5.1.0/GKlib/blas.c
src/Cluster_Ensembles/Hypergraph_Partitioning/metis-5.1.0/GKlib/csr.c
src/Cluster_Ensembles/Hypergraph_Partitioning/metis-5.1.0/GKlib/error.c
src/Cluster_Ensembles/Hypergraph_Partitioning/metis-5.1.0/GKlib/evaluate.c
src/Cluster_Ensembles/Hypergraph_Partitioning/metis-5.1.0/GKlib/fkvkselect.c
src/Cluster_Ensembles/Hypergraph_Partitioning/metis-5.1.0/GKlib/fs.c
